{
  "schema": "leitor-faturas-global-rules",
  "version": 4,
  "updatedAt": "2026-07-11T22:49:55.661Z",
  "rules": {
    "ignore_terms": [
      "ENCARGOS DE ROTATIVO",
      "IOF OPER.CRED ROT",
      "PARC.FACI",
      "IOF DIARIO ROTATIVO",
      "ENCARGOS FINANCIAMENTO",
      "JUROS DE ROTATIVO",
      "IOF",
      "ENCARGOS FINANCIAMENTO ATRASO",
      "ENCARGOS DE SAQUE",
      "EST COBR SEG PAN PRESTAMI",
      "ESTORNO IOF - P",
      "EST ENC ROTAT.M",
      "REVERSAO SALDO",
      "REVERSAO SEGURO PRESTAMISTA",
      "IOF - P",
      "PARCELAMIN138",
      "REVIOFADICIONAL",
      "AJUSTESEGURO",
      "IMPOSTO OP FIN - DIARIO",
      "DEVOL.DESC.FOLHA",
      "IMPOSTO OP FIN DIARIO",
      "IMPOSTO OP FIN",
      "IMPOSTO OP FIN - ADICIONAL",
      "IOF ADIC ROTATIVO",
      "IOF ADICIONAL",
      "TARIFA DE EMISSAO",
      "ENCARGOS DE ATRASO",
      "ENCARGOS DE MORA",
      "DEVOLUCAO TARIFA SAQUE",
      "DEVOLUÇÃO TARIFA SAQUE",
      "PAG BOLETO BANCARIO",
      "PAGAMENTO BOLETO BANCARIO",
      "REV PAGAMENTO CRED C C",
      "REV PAGAMENTO CRED CC",
      "REV PGTO CRED C C",
      "REV PGTO CRED CC",
      "REVPAGAMENTOCREDCC",
      "REEMBOLSO DE SALDO CREDOR",
      "LIMITE DISPONIVEL",
      "LIMITE UTILIZADO",
      "DISPONIVEL",
      "VALOR DA FATURA",
      "PAGAMENTO MINIMO",
      "TOTAL A PAGAR",
      "TOTAL DE COMPRAS PARCELADAS",
      "COMPRAS PARCELADAS A VENCER",
      "DATA PREVISTA DE FECHAMENTO",
      "ENCARGOS DE FINANCIAMENTO",
      "REV PGTO EM FOLHA"
    ],
    "payroll_terms": [
      "PAGAMENTO DEBITO EM FOLHA",
      "PGTO CONSIGNADO",
      "PGTO DESCONTO EM FOLHA",
      "DEB FOLHA PGTO"
    ],
    "insurance_terms": [
      "COBR SEG PAN PRESTAMISTA",
      "SEGURO PRESTAMISTA",
      "SEGUROCARTAOPAN"
    ],
    "cash_advance_terms": [
      "TELESAQUE A VISTA",
      "TELESAQUE",
      "SAQUE A VISTA"
    ],
    "payment_terms": [
      "PAGAMENTO EFETUADO",
      "PAGAMENTO BOLETO",
      "PAGAMENTO DE BOLETO",
      "PAG BOLETO BANCARIO",
      "PAGAMENTO BOLETO BANCARIO"
    ],
    "purchase_terms": []
  }
}
